las/__init__.py
las/__version__.py
las/client.py
las/credentials.py
lucidtech_las-11.4.1.dist-info/LICENSE.md
lucidtech_las-11.4.1.dist-info/METADATA
lucidtech_las-11.4.1.dist-info/WHEEL
lucidtech_las-11.4.1.dist-info/top_level.txt
lucidtech_las-11.4.1.dist-info/RECORD
