Metadata-Version: 2.1
Name: lucidtech-las
Version: 11.4.1
Summary: Python SDK for Lucidtech AI Services
Home-page: https://github.com/LucidtechAI/las-sdk-python
Author: Lucidtech
Author-email: hello@lucidtech.ai
Maintainer: Magnus Aarskaug Rud
Maintainer-email: magnus@lucidtech.ai
License: Apache 2.0
Platform: Posix; MacOS X; Windows
Classifier: Development Status :: 5 - Production/Stable
Classifier: Intended Audience :: Developers
Classifier: License :: OSI Approved :: Apache Software License
Classifier: Operating System :: OS Independent
Classifier: Programming Language :: Python :: 3.8
Classifier: Programming Language :: Python :: 3.9
Classifier: Programming Language :: Python :: 3.10
Classifier: Programming Language :: Python :: 3.11
Classifier: Topic :: Internet
License-File: LICENSE.md
Requires-Dist: requests
Requires-Dist: backoff
Requires-Dist: filetype
